wickes_tools/__init__.py
wickes_tools/cal1/__init__.py
wickes_tools/cal1/cal2.py
wickes_tools/cal1/cal3.py
wickes_tools/cal4/__init__.py
wickes_tools/cal4/cal5.py
wickes_tools-0.0.4.dist-info/LICENSE
wickes_tools-0.0.4.dist-info/METADATA
wickes_tools-0.0.4.dist-info/WHEEL
wickes_tools-0.0.4.dist-info/top_level.txt
wickes_tools-0.0.4.dist-info/RECORD
