Metadata-Version: 2.1
Name: wickes-tools
Version: 0.0.4
Summary: code collection
Home-page: https://github.com/1wickes/wickes-tools
Author: 
Author-email: 
License: MIT
Keywords: collections
Platform: UNKNOWN
Classifier: Development Status :: 5 - Production/Stable
Classifier: Intended Audience :: Education
Classifier: Operating System :: Microsoft :: Windows :: Windows 10
Classifier: License :: OSI Approved :: MIT License
Classifier: Programming Language :: Python :: 3
